{
  "The KGB still operates in which European country?": "Belarus",
  "Which style of jazz singing puts words to existing melodies or solos?": "Vocalese (not scat)",
  "Who now sponsors the Women's Prize for Fiction?": "Baileys",
  "Which cabinet member is the son of a flying ace and a ballerina?": "Iain Duncan Smith",
  "Which language is known as Ivrit to its speakers?": "Hebrew",
  "Who receives the Commissioner's Trophy?": "Baseball World Series winners",
  "\"Curst be he that moves my bones\" is written on whose tomb?": "Shakespeare",
  "After Crete, what is the next largest Greek island?": "Euboea",
  "JS Bach; GF Handel; Domenico Scarlatti?": "Born in 1685",
  "Yde; Lindow; Tollund; Weerdinge; Old Croghan; Gallagh?": "Location of bog body discoveries",
  "Dandie Dinmont; Bedlington; Glen Of Imaal; Skye; Cairn?": "Terrier breeds",
  "Victoria Wood; Marti Caine; Lenny Henry; Michael Barrymore; Les Dennis?": "Appeared on ITV's New Faces",
  "Lion; eagle; cannon; cockerel; castle?": "Emblems on London Premier League club badges: Chelsea; Crystal Palace; Arsenal; Spurs; West Ham",
  "Through The Looking Glass; The Luzhin Defence; The Royal Game; The Big Four?": "Chess-themed fictional works: Lewis Carroll; Vladimir Nabokov; Stefan Zweig; Agatha Christie",
  "Olfactory; optic; facial; trochlear; vagus; hypoglossal (and six others)?": "Cranial nerves"
}