{
  "What phrase derives from a 1977 episode of Happy Days?": "Jumping the shark",
  "In 1801, what was the first asteroid to be discovered?": "Ceres",
  "The Adi Granth are scriptures of which religion?": "Sikhism",
  "Elevation Partners is which singer's investment firm?": "Bono",
  "Where is Bishop Grosseteste University?": "Lincoln",
  "The French comedian Dieudonn\u00e9\u00a0devised what controversial gesture?": "The Quenelle salute",
  "Hokusai created 36 views of what?": "Mount Fuji",
  "Curtain was whose curtain call?": "It was Hercule Poirot's last case"
}