{
  "The Disney film White Wilderness is the origin of what animal myth?": "Lemmings kill themselves en masse",
  "What 1714 act was read literally, now metaphorically?": "Riot Act",
  "Which sculpture museum is in Florence's Palazzo del Podest\u00e0?": "The Bargello",
  "What sports team is owned by the US ambassador to the UK?": "New York Jets (Woody Johnson)",
  "\"Where do you want to go today?\" was whose slogan?": "Microsoft",
  "Queen Victoria lent which gem to the Great Exhibition?": "Koh-i-Noor diamond",
  "In the USSR, what was Komsomol?": "Communist youth movement"
}