{
  "What are counted \"Yan, tan, tether, mether...\"?": "Sheep (in Swaledale)",
  "Which shop was built from the timbers of HMS Impregnable and Hindustan?": "Liberty",
  "Where in the body is the organ of Corti?": "Cochlea/inner ear",
  "Which film features the bank-robbing Ex-Presidents?": "Point Break",
  "What is the only distillery on the Isle of Skye?": "Talisker",
  "Which album cover shows goats being fed at San Diego zoo?": "Pet Sounds by the Beach Boys",
  "What was founded by Octavia Hill, Robert Hunter and Hardwicke Rawnsley?": "The National Trust",
  "What shape are Gugelhupf and ciambella cakes?": "Ring-shaped",
  "Anastasia Steele; Yossarian; Winston Smith; Richard Hannay?": "In numbered novels: Fifty Shades Of Grey; Catch-22; Nineteen Eighty-Four; The Thirty-Nine Steps",
  "Scottish (14); Italian, French and Portuguese (all three); Chilean (one)?": "Premier League managers, wins by nationality",
  "St John's, Newfoundland and Clifden, Galway, 14-15 June 1919?": "First nonstop transatlantic flight (by Alcock and Brown)",
  "Becquerel; gray; sievert?": "Derived SI units measuring radiation: radioactivity; absorbed dose; dose equivalent",
  "Broom; Cinnabar; Scalloped Oak; Puss; Jersey Tiger?": "British moths",
  "Air and Space; Art; Natural History; American History; African American History (19th, in 2016)?": "Smithsonian museums",
  "Wentworth; Litchfield; Stone Park; Larkhall?": "Fictional women's prisons: Prisoner: Cell Block H; Orange Is The New Black; Within These Walls; Bad Girls"
}