{
  "What was recorded at Sarm West Studios on 25 November 1984?": "Band Aid's Do They Know It's Christmas?",
  "Ercole Mattioli and Eustache Dauger are proposed identities for which prisoner?": "Man in the Iron Mask",
  "The Norse god Baldr was killed by a spear made of what?": "Mistletoe",
  "Who followed Charles Hamilton and Frank Kennedy?": "Rhett Butler (husbands of Scarlett O'Hara in Gone With the Wind)",
  "Which tennis venue is named after a first world war fighter pilot?": "Roland Garros (Paris)",
  "What was \"made in Scotland from girders\"?": "Irn-Bru drink",
  "Edith Holden's Nature Notes for 1906 become a bestseller under what title?": "The Country Diary of an Edwardian Lady",
  "In London motoring, what is the ULEZ?": "Ultra-low emission zone"
}